[{"code":"","color":"#FF000000","name":"created ","typeName":"","palette":"241","type":"h","spec":"       \"      بلوک ویرایش سرور    \"          "},{"code":"%2$s \u003d new HashMap\u003c\u003e();\r\n%2$s.put(\"name\", %3$s);\n%2$s.put(\"password\", %4$s);\n%2$s.put(\"text\", %5$s);\n%1$s.setParams(%2$s, RequestNetworkController.REQUEST_PARAM);\r\n%1$s.startRequestNetwork(RequestNetworkController.POST, \"http://e-server.ir/s/edit.php\", \"\", _%1$s_request_listener);","color":"#FF003AFF","name":"Map-Send- ESERVER","typeName":"Map-Send","palette":"241","type":" ","spec":"E SERVER edit :‌ *request* %m.requestnetwork *map* %m.varMap *name* %s *password* %s *text* %s  "},{"code":"","color":"#FF000000","name":"created ","typeName":"","palette":"241","type":"h","spec":"       \"      بلوک ساخت سرور    \"          "},{"code":"%2$s \u003d new HashMap\u003c\u003e();\n%2$s.put(\"username\", %3$s);\n%2$s.put(\"password\", %4$s);\r\n%2$s.put(\"name\", %5$s);\n%2$s.put(\"password2\", %6$s);\n%1$s.setParams(%2$s, RequestNetworkController.REQUEST_PARAM);\r\n%1$s.startRequestNetwork(RequestNetworkController.POST, \"http://e-server.ir/s/add.php\", \"\", _%1$s_request_listener);","color":"#FF003AFF","name":"Map-Create-ESERVER","typeName":"Map-Create-E SERVER","palette":"241","type":" ","spec":"ESERVER create : *request* %m.requestnetwork *map* %m.varMap *username* %s *password* %s *name* %s *passwords* %s "},{"code":"","color":"#000000","name":"","typeName":"","palette":"241","type":"h","spec":"       \"      بلوک حذف سرور    \"          "},{"code":"%2$s \u003d new HashMap\u003c\u003e();\n%2$s.put(\"name\", %3$s);\r\n%2$s.put(\"password\", %4$s);\n%1$s.setParams(%2$s, RequestNetworkController.REQUEST_PARAM);\r\n%1$s.startRequestNetwork(RequestNetworkController.POST, \"http://e-server.ir/s/delete.php\", \"\", _%1$s_request_listener);","color":"#FF003AFF","name":"Map-Delete-ESERVER","typeName":"Map-Delete-ESERVER","palette":"241","type":" ","spec":"ESERVER delete :  *request* %m.requestnetwork *map* %m.varMap *name* %s *password* %s  "}]